charmarr_lib/core/__init__.py
charmarr_lib/core/_variant.py
charmarr_lib/core/_version.py
charmarr_lib/core/constants.py
charmarr_lib/core/enums.py
charmarr_lib/core/_arr/__init__.py
charmarr_lib/core/_arr/_arr_client.py
charmarr_lib/core/_arr/_base_client.py
charmarr_lib/core/_arr/_config_builders.py
charmarr_lib/core/_arr/_config_xml.py
charmarr_lib/core/_arr/_protocols.py
charmarr_lib/core/_arr/_reconcilers.py
charmarr_lib/core/_arr/_recyclarr.py
charmarr_lib/core/_juju/__init__.py
charmarr_lib/core/_juju/_pebble.py
charmarr_lib/core/_juju/_reconciler.py
charmarr_lib/core/_juju/_secrets.py
charmarr_lib/core/_k8s/__init__.py
charmarr_lib/core/_k8s/_hardware.py
charmarr_lib/core/_k8s/_permission_check.py
charmarr_lib/core/_k8s/_storage.py
charmarr_lib/core/interfaces/__init__.py
charmarr_lib/core/interfaces/_base.py
charmarr_lib/core/interfaces/_download_client.py
charmarr_lib/core/interfaces/_flaresolverr.py
charmarr_lib/core/interfaces/_media_indexer.py
charmarr_lib/core/interfaces/_media_manager.py
charmarr_lib/core/interfaces/_media_server.py
charmarr_lib/core/interfaces/_media_storage.py
charmarr_lib_core-0.12.2.dist-info/METADATA
charmarr_lib_core-0.12.2.dist-info/WHEEL
charmarr_lib_core-0.12.2.dist-info/RECORD
